<?xml version="1.0" encoding="utf-8"?>
<SoundBanksInfo Platform="Windows" BasePlatform="Windows" SchemaVersion="12" SoundbankVersion="135">
	<RootPaths>
		<ProjectRoot>C:\Users\migue\Desktop\Projetos\CursedProject\Assets\CursedProject_WwiseProject\</ProjectRoot>
		<SourceFilesRoot>C:\Users\migue\Desktop\Projetos\CursedProject\Assets\CursedProject_WwiseProject\.cache\Windows\</SourceFilesRoot>
		<SoundBanksRoot>C:\Users\migue\Desktop\Projetos\CursedProject\Assets\CursedProject_WwiseProject\GeneratedSoundBanks\Windows\</SoundBanksRoot>
		<ExternalSourcesInputFile></ExternalSourcesInputFile>
		<ExternalSourcesOutputRoot>C:\Users\migue\Desktop\Projetos\CursedProject\Assets\CursedProject_WwiseProject\GeneratedSoundBanks\Windows</ExternalSourcesOutputRoot>
	</RootPaths>
	<DialogueEvents/>
	<StreamedFiles/>
	<MediaFilesNotInAnyBank/>
	<SoundBanks>
		<SoundBank Id="1355168291" Language="SFX" Hash="807542745">
			<ObjectPath>Init</ObjectPath>
			<ShortName>Init</ShortName>
			<Path>Init.bnk</Path>
			<GameParameters>
				<GameParameter Id="988953028" Name="SFXVolume" ObjectPath="\Game Parameters\Default Work Unit\SFXVolume"/>
				<GameParameter Id="2627017276" Name="RTPC_Reverb_2" ObjectPath="\Game Parameters\Default Work Unit\RTPC_Reverb_2"/>
				<GameParameter Id="4143461479" Name="RTPC_Reverb" ObjectPath="\Game Parameters\Default Work Unit\RTPC_Reverb"/>
			</GameParameters>
		</SoundBank>
		<SoundBank Id="2879190521" Language="SFX" Hash="1386416949">
			<ObjectPath>\SoundBanks\Default Work Unit\ForTests</ObjectPath>
			<ShortName>ForTests</ShortName>
			<Path>ForTests.bnk</Path>
			<IncludedEvents>
				<Event Id="369930381" Name="GyaruPlayAttackLong" ObjectPath="\Events\Players\Gyaru\GyaruPlayAttackLong" MaxAttenuation="40.000000" DurationType="Infinite">
					<IncludedMemoryFiles>
						<File Id="321833020" Language="SFX">
							<ShortName>PlayerWeapons\Gyaru\Long.wav</ShortName>
							<Path>SFX\PlayerWeapons\Gyaru\Long_7AFCE640.wem</Path>
						</File>
					</IncludedMemoryFiles>
				</Event>
				<Event Id="166469259" Name="GyaruPlayAttackShort" ObjectPath="\Events\Players\Gyaru\GyaruPlayAttackShort" MaxAttenuation="40.000000" DurationType="Infinite">
					<IncludedMemoryFiles>
						<File Id="153084191" Language="SFX">
							<ShortName>PlayerWeapons\Gyaru\Short.wav</ShortName>
							<Path>SFX\PlayerWeapons\Gyaru\Short_234839FD.wem</Path>
						</File>
					</IncludedMemoryFiles>
				</Event>
				<Event Id="3302019815" Name="GyaruStopAttackLong" ObjectPath="\Events\Players\Gyaru\GyaruStopAttackLong" MaxAttenuation="40.000000" DurationType="OneShot" DurationMin="0.112177" DurationMax="0.112177">
					<IncludedMemoryFiles>
						<File Id="823667250" Language="SFX">
							<ShortName>PlayerWeapons\Gyaru\LongTail.wav</ShortName>
							<Path>SFX\PlayerWeapons\Gyaru\LongTail_10C4C929.wem</Path>
						</File>
					</IncludedMemoryFiles>
				</Event>
				<Event Id="2650513656" Name="PlayAmbiance1" ObjectPath="\Events\Ambiances\PlayAmbiance1" DurationType="Infinite">
					<IncludedMemoryFiles>
						<File Id="387338394" Language="SFX">
							<ShortName>Ambiances\WindCity1.wav</ShortName>
							<Path>SFX\Ambiances\WindCity1_77FE18DF.wem</Path>
						</File>
					</IncludedMemoryFiles>
				</Event>
				<Event Id="3131532911" Name="PlayAmbianceJanitorRoom" ObjectPath="\Events\Ambiances\PlayAmbianceJanitorRoom" DurationType="Infinite">
					<IncludedMemoryFiles>
						<File Id="96390048" Language="SFX">
							<ShortName>Ambiances\Janitor House\Air Vent 1.wav</ShortName>
							<Path>SFX\Ambiances\Janitor House\Air Vent 1_D79FB2B7.wem</Path>
						</File>
						<File Id="285837040" Language="SFX">
							<ShortName>Ambiances\Janitor House\MetalClang3.wav</ShortName>
							<Path>SFX\Ambiances\Janitor House\MetalClang3_10C4C929.wem</Path>
						</File>
						<File Id="607129376" Language="SFX">
							<ShortName>Ambiances\Janitor House\MetalClang2.wav</ShortName>
							<Path>SFX\Ambiances\Janitor House\MetalClang2_10C4C929.wem</Path>
						</File>
						<File Id="780781574" Language="SFX">
							<ShortName>Ambiances\Janitor House\MetalClang1.wav</ShortName>
							<Path>SFX\Ambiances\Janitor House\MetalClang1_10C4C929.wem</Path>
						</File>
					</IncludedMemoryFiles>
				</Event>
				<Event Id="204688551" Name="PlayAttack2" ObjectPath="\Events\Enemies\Chicken\PlayAttack2" MaxAttenuation="40.000000" DurationType="OneShot" DurationMin="0.500000" DurationMax="0.500000">
					<IncludedMemoryFiles>
						<File Id="51034049" Language="SFX">
							<ShortName>Chicken\Attack\atack 2.wav</ShortName>
							<Path>SFX\Chicken\Attack\atack 2_10C4C929.wem</Path>
						</File>
					</IncludedMemoryFiles>
				</Event>
				<Event Id="204688550" Name="PlayAttack3" ObjectPath="\Events\Enemies\Chicken\PlayAttack3" MaxAttenuation="40.000000" DurationType="OneShot" DurationMin="0.500000" DurationMax="0.500000">
					<IncludedMemoryFiles>
						<File Id="856417953" Language="SFX">
							<ShortName>Chicken\Attack\atack 3.1.wav</ShortName>
							<Path>SFX\Chicken\Attack\atack 3.1_10C4C929.wem</Path>
						</File>
						<File Id="899381549" Language="SFX">
							<ShortName>Chicken\Attack\atack 3.2.wav</ShortName>
							<Path>SFX\Chicken\Attack\atack 3.2_10C4C929.wem</Path>
						</File>
					</IncludedMemoryFiles>
				</Event>
				<Event Id="2629272678" Name="PlayBackstab" ObjectPath="\Events\Enemies\Chicken\PlayBackstab" MaxAttenuation="40.000000" DurationType="OneShot" DurationMin="0.500000" DurationMax="0.500000">
					<IncludedMemoryFiles>
						<File Id="1023060161" Language="SFX">
							<ShortName>Chicken\Attack\Backstab2.wav</ShortName>
							<Path>SFX\Chicken\Attack\Backstab2_10C4C929.wem</Path>
						</File>
					</IncludedMemoryFiles>
				</Event>
				<Event Id="1470550983" Name="PlayChickenChasing" ObjectPath="\Events\Enemies\Chicken\PlayChickenChasing" MaxAttenuation="40.000000" DurationType="OneShot" DurationMin="1.076124" DurationMax="2.648658">
					<IncludedMemoryFiles>
						<File Id="128794003" Language="SFX">
							<ShortName>Chicken\Vocal\Chase\Chase7.wav</ShortName>
							<Path>SFX\Chicken\Vocal\Chase\Chase7_10C4C929.wem</Path>
						</File>
						<File Id="405905271" Language="SFX">
							<ShortName>Chicken\Vocal\Chase\Chase4.wav</ShortName>
							<Path>SFX\Chicken\Vocal\Chase\Chase4_10C4C929.wem</Path>
						</File>
						<File Id="406351538" Language="SFX">
							<ShortName>Chicken\Vocal\Chase\Chase3.wav</ShortName>
							<Path>SFX\Chicken\Vocal\Chase\Chase3_10C4C929.wem</Path>
						</File>
						<File Id="525871147" Language="SFX">
							<ShortName>Chicken\Vocal\Chase\Chase1.wav</ShortName>
							<Path>SFX\Chicken\Vocal\Chase\Chase1_10C4C929.wem</Path>
						</File>
						<File Id="551745069" Language="SFX">
							<ShortName>Chicken\Vocal\Chase\Chase5.wav</ShortName>
							<Path>SFX\Chicken\Vocal\Chase\Chase5_10C4C929.wem</Path>
						</File>
						<File Id="557898274" Language="SFX">
							<ShortName>Chicken\Vocal\Chase\Chase6.wav</ShortName>
							<Path>SFX\Chicken\Vocal\Chase\Chase6_10C4C929.wem</Path>
						</File>
						<File Id="1030892577" Language="SFX">
							<ShortName>Chicken\Vocal\Chase\Chase2.wav</ShortName>
							<Path>SFX\Chicken\Vocal\Chase\Chase2_10C4C929.wem</Path>
						</File>
					</IncludedMemoryFiles>
				</Event>
				<Event Id="2892866942" Name="PlayChickenDie" ObjectPath="\Events\Enemies\Chicken\PlayChickenDie" MaxAttenuation="40.000000" DurationType="OneShot" DurationMin="1.102966" DurationMax="1.781797">
					<IncludedMemoryFiles>
						<File Id="170623511" Language="SFX">
							<ShortName>Chicken\Vocal\Die\Die3.wav</ShortName>
							<Path>SFX\Chicken\Vocal\Die\Die3_10C4C929.wem</Path>
						</File>
						<File Id="407949984" Language="SFX">
							<ShortName>Chicken\Vocal\Die\Die1.wav</ShortName>
							<Path>SFX\Chicken\Vocal\Die\Die1_10C4C929.wem</Path>
						</File>
						<File Id="930833694" Language="SFX">
							<ShortName>Chicken\Vocal\Die\Die2.wav</ShortName>
							<Path>SFX\Chicken\Vocal\Die\Die2_10C4C929.wem</Path>
						</File>
					</IncludedMemoryFiles>
				</Event>
				<Event Id="196258217" Name="PlayChickenFootsteps" ObjectPath="\Events\Enemies\Chicken\PlayChickenFootsteps" MaxAttenuation="40.000000" DurationType="OneShot" DurationMin="0.485766" DurationMax="0.514651">
					<IncludedMemoryFiles>
						<File Id="134553406" Language="SFX">
							<ShortName>Chicken\Footstep\chicken fs2.wav</ShortName>
							<Path>SFX\Chicken\Footstep\chicken fs2_10C4C929.wem</Path>
						</File>
						<File Id="615928074" Language="SFX">
							<ShortName>Chicken\Footstep\chicken fs1.wav</ShortName>
							<Path>SFX\Chicken\Footstep\chicken fs1_10C4C929.wem</Path>
						</File>
						<File Id="747551622" Language="SFX">
							<ShortName>Chicken\Footstep\chicken fs4.wav</ShortName>
							<Path>SFX\Chicken\Footstep\chicken fs4_10C4C929.wem</Path>
						</File>
						<File Id="864817520" Language="SFX">
							<ShortName>Chicken\Footstep\chicken fs3.wav</ShortName>
							<Path>SFX\Chicken\Footstep\chicken fs3_10C4C929.wem</Path>
						</File>
					</IncludedMemoryFiles>
				</Event>
				<Event Id="3029059251" Name="PlayChickenHit" ObjectPath="\Events\Enemies\Chicken\PlayChickenHit" MaxAttenuation="40.000000" DurationType="OneShot" DurationMin="0.345283" DurationMax="0.610952">
					<IncludedMemoryFiles>
						<File Id="203460149" Language="SFX">
							<ShortName>Chicken\Vocal\Hit\Hit3.wav</ShortName>
							<Path>SFX\Chicken\Vocal\Hit\Hit3_10C4C929.wem</Path>
						</File>
						<File Id="528793756" Language="SFX">
							<ShortName>Chicken\Vocal\Hit\Hit1.wav</ShortName>
							<Path>SFX\Chicken\Vocal\Hit\Hit1_10C4C929.wem</Path>
						</File>
						<File Id="788155044" Language="SFX">
							<ShortName>Chicken\Vocal\Hit\Hit2.wav</ShortName>
							<Path>SFX\Chicken\Vocal\Hit\Hit2_10C4C929.wem</Path>
						</File>
					</IncludedMemoryFiles>
				</Event>
				<Event Id="2039287504" Name="PlayChickenOnSpawn" ObjectPath="\Events\Enemies\Chicken\PlayChickenOnSpawn" MaxAttenuation="40.000000" DurationType="Infinite">
					<IncludedMemoryFiles>
						<File Id="1876340" Language="SFX">
							<ShortName>Chicken\Vocal\Eager\EagerFinal1.wav</ShortName>
							<Path>SFX\Chicken\Vocal\Eager\EagerFinal1_10C4C929.wem</Path>
						</File>
						<File Id="15091794" Language="SFX">
							<ShortName>Chicken\Vocal\Eager\EagerFinal3.wav</ShortName>
							<Path>SFX\Chicken\Vocal\Eager\EagerFinal3_10C4C929.wem</Path>
						</File>
						<File Id="25723946" Language="SFX">
							<ShortName>Chicken\Vocal\Eager\Eager5.wav</ShortName>
							<Path>SFX\Chicken\Vocal\Eager\Eager5_10C4C929.wem</Path>
						</File>
						<File Id="230421140" Language="SFX">
							<ShortName>Chicken\Vocal\Eager\Eager10.wav</ShortName>
							<Path>SFX\Chicken\Vocal\Eager\Eager10_10C4C929.wem</Path>
						</File>
						<File Id="234818940" Language="SFX">
							<ShortName>Chicken\Vocal\Eager\Eager4.wav</ShortName>
							<Path>SFX\Chicken\Vocal\Eager\Eager4_10C4C929.wem</Path>
						</File>
						<File Id="290978038" Language="SFX">
							<ShortName>Chicken\Vocal\Eager\Eager3.wav</ShortName>
							<Path>SFX\Chicken\Vocal\Eager\Eager3_10C4C929.wem</Path>
						</File>
						<File Id="436521656" Language="SFX">
							<ShortName>Chicken\Vocal\Eager\Eager12.wav</ShortName>
							<Path>SFX\Chicken\Vocal\Eager\Eager12_10C4C929.wem</Path>
						</File>
						<File Id="476393637" Language="SFX">
							<ShortName>Chicken\Vocal\Eager\Eager7.wav</ShortName>
							<Path>SFX\Chicken\Vocal\Eager\Eager7_10C4C929.wem</Path>
						</File>
						<File Id="562183493" Language="SFX">
							<ShortName>Chicken\Vocal\Eager\Eager11.wav</ShortName>
							<Path>SFX\Chicken\Vocal\Eager\Eager11_10C4C929.wem</Path>
						</File>
						<File Id="697692854" Language="SFX">
							<ShortName>Chicken\Vocal\Eager\Eager9.wav</ShortName>
							<Path>SFX\Chicken\Vocal\Eager\Eager9_10C4C929.wem</Path>
						</File>
						<File Id="701243151" Language="SFX">
							<ShortName>Chicken\Vocal\Eager\EagerFinal2.wav</ShortName>
							<Path>SFX\Chicken\Vocal\Eager\EagerFinal2_10C4C929.wem</Path>
						</File>
						<File Id="831035638" Language="SFX">
							<ShortName>Chicken\Vocal\Eager\Eager1.wav</ShortName>
							<Path>SFX\Chicken\Vocal\Eager\Eager1_10C4C929.wem</Path>
						</File>
						<File Id="895691896" Language="SFX">
							<ShortName>Chicken\Vocal\Eager\Eager2.wav</ShortName>
							<Path>SFX\Chicken\Vocal\Eager\Eager2_10C4C929.wem</Path>
						</File>
						<File Id="1023437812" Language="SFX">
							<ShortName>Chicken\Vocal\Eager\Eager6.wav</ShortName>
							<Path>SFX\Chicken\Vocal\Eager\Eager6_10C4C929.wem</Path>
						</File>
						<File Id="1037537274" Language="SFX">
							<ShortName>Chicken\Vocal\Eager\Eager8.wav</ShortName>
							<Path>SFX\Chicken\Vocal\Eager\Eager8_10C4C929.wem</Path>
						</File>
					</IncludedMemoryFiles>
				</Event>
				<Event Id="4042026069" Name="PlayChickenRunAway" ObjectPath="\Events\Enemies\Chicken\PlayChickenRunAway" MaxAttenuation="40.000000" DurationType="OneShot" DurationMin="1.196269" DurationMax="2.118926">
					<IncludedMemoryFiles>
						<File Id="246445162" Language="SFX">
							<ShortName>Chicken\Vocal\Run Away\RunAway1.wav</ShortName>
							<Path>SFX\Chicken\Vocal\Run Away\RunAway1_10C4C929.wem</Path>
						</File>
						<File Id="312019833" Language="SFX">
							<ShortName>Chicken\Vocal\Run Away\RunAway4.wav</ShortName>
							<Path>SFX\Chicken\Vocal\Run Away\RunAway4_10C4C929.wem</Path>
						</File>
						<File Id="540739948" Language="SFX">
							<ShortName>Chicken\Vocal\Run Away\RunAway3.wav</ShortName>
							<Path>SFX\Chicken\Vocal\Run Away\RunAway3_10C4C929.wem</Path>
						</File>
						<File Id="833753326" Language="SFX">
							<ShortName>Chicken\Vocal\Run Away\RunAway5.wav</ShortName>
							<Path>SFX\Chicken\Vocal\Run Away\RunAway5_10C4C929.wem</Path>
						</File>
						<File Id="986628007" Language="SFX">
							<ShortName>Chicken\Vocal\Run Away\RunAway2.wav</ShortName>
							<Path>SFX\Chicken\Vocal\Run Away\RunAway2_10C4C929.wem</Path>
						</File>
					</IncludedMemoryFiles>
				</Event>
				<Event Id="1378272331" Name="PlayChickenWatching" ObjectPath="\Events\Enemies\Chicken\PlayChickenWatching" MaxAttenuation="40.000000" DurationType="OneShot" DurationMin="2.442601" DurationMax="5.786951">
					<IncludedMemoryFiles>
						<File Id="1876340" Language="SFX">
							<ShortName>Chicken\Vocal\Eager\EagerFinal1.wav</ShortName>
							<Path>SFX\Chicken\Vocal\Eager\EagerFinal1_10C4C929.wem</Path>
						</File>
						<File Id="15091794" Language="SFX">
							<ShortName>Chicken\Vocal\Eager\EagerFinal3.wav</ShortName>
							<Path>SFX\Chicken\Vocal\Eager\EagerFinal3_10C4C929.wem</Path>
						</File>
						<File Id="25723946" Language="SFX">
							<ShortName>Chicken\Vocal\Eager\Eager5.wav</ShortName>
							<Path>SFX\Chicken\Vocal\Eager\Eager5_10C4C929.wem</Path>
						</File>
						<File Id="230421140" Language="SFX">
							<ShortName>Chicken\Vocal\Eager\Eager10.wav</ShortName>
							<Path>SFX\Chicken\Vocal\Eager\Eager10_10C4C929.wem</Path>
						</File>
						<File Id="234818940" Language="SFX">
							<ShortName>Chicken\Vocal\Eager\Eager4.wav</ShortName>
							<Path>SFX\Chicken\Vocal\Eager\Eager4_10C4C929.wem</Path>
						</File>
						<File Id="290978038" Language="SFX">
							<ShortName>Chicken\Vocal\Eager\Eager3.wav</ShortName>
							<Path>SFX\Chicken\Vocal\Eager\Eager3_10C4C929.wem</Path>
						</File>
						<File Id="436521656" Language="SFX">
							<ShortName>Chicken\Vocal\Eager\Eager12.wav</ShortName>
							<Path>SFX\Chicken\Vocal\Eager\Eager12_10C4C929.wem</Path>
						</File>
						<File Id="476393637" Language="SFX">
							<ShortName>Chicken\Vocal\Eager\Eager7.wav</ShortName>
							<Path>SFX\Chicken\Vocal\Eager\Eager7_10C4C929.wem</Path>
						</File>
						<File Id="562183493" Language="SFX">
							<ShortName>Chicken\Vocal\Eager\Eager11.wav</ShortName>
							<Path>SFX\Chicken\Vocal\Eager\Eager11_10C4C929.wem</Path>
						</File>
						<File Id="697692854" Language="SFX">
							<ShortName>Chicken\Vocal\Eager\Eager9.wav</ShortName>
							<Path>SFX\Chicken\Vocal\Eager\Eager9_10C4C929.wem</Path>
						</File>
						<File Id="701243151" Language="SFX">
							<ShortName>Chicken\Vocal\Eager\EagerFinal2.wav</ShortName>
							<Path>SFX\Chicken\Vocal\Eager\EagerFinal2_10C4C929.wem</Path>
						</File>
						<File Id="831035638" Language="SFX">
							<ShortName>Chicken\Vocal\Eager\Eager1.wav</ShortName>
							<Path>SFX\Chicken\Vocal\Eager\Eager1_10C4C929.wem</Path>
						</File>
						<File Id="895691896" Language="SFX">
							<ShortName>Chicken\Vocal\Eager\Eager2.wav</ShortName>
							<Path>SFX\Chicken\Vocal\Eager\Eager2_10C4C929.wem</Path>
						</File>
						<File Id="1023437812" Language="SFX">
							<ShortName>Chicken\Vocal\Eager\Eager6.wav</ShortName>
							<Path>SFX\Chicken\Vocal\Eager\Eager6_10C4C929.wem</Path>
						</File>
						<File Id="1037537274" Language="SFX">
							<ShortName>Chicken\Vocal\Eager\Eager8.wav</ShortName>
							<Path>SFX\Chicken\Vocal\Eager\Eager8_10C4C929.wem</Path>
						</File>
					</IncludedMemoryFiles>
				</Event>
				<Event Id="3831688773" Name="PlayerHit" ObjectPath="\Events\Players\PlayerHit" MaxAttenuation="40.000000" DurationType="OneShot" DurationMin="0.334966" DurationMax="1.500000">
					<IncludedMemoryFiles>
						<File Id="44541559" Language="SFX">
							<ShortName>Shards\shards hit1.wav</ShortName>
							<Path>SFX\Shards\shards hit1_10C4C929.wem</Path>
						</File>
						<File Id="218867492" Language="SFX">
							<ShortName>Chicken\Attack\PlayerHitByChicken2.wav</ShortName>
							<Path>SFX\Chicken\Attack\PlayerHitByChicken2_10C4C929.wem</Path>
						</File>
						<File Id="229165378" Language="SFX">
							<ShortName>Shards\shards hit3.wav</ShortName>
							<Path>SFX\Shards\shards hit3_10C4C929.wem</Path>
						</File>
						<File Id="468032026" Language="SFX">
							<ShortName>Shards\shards hit6.wav</ShortName>
							<Path>SFX\Shards\shards hit6_10C4C929.wem</Path>
						</File>
						<File Id="709017288" Language="SFX">
							<ShortName>Shards\shards hit2.wav</ShortName>
							<Path>SFX\Shards\shards hit2_10C4C929.wem</Path>
						</File>
						<File Id="715216894" Language="SFX">
							<ShortName>Shards\shards hit4.wav</ShortName>
							<Path>SFX\Shards\shards hit4_10C4C929.wem</Path>
						</File>
						<File Id="835120531" Language="SFX">
							<ShortName>Shards\shards hit5.wav</ShortName>
							<Path>SFX\Shards\shards hit5_10C4C929.wem</Path>
						</File>
						<File Id="898080531" Language="SFX">
							<ShortName>Chicken\Attack\PlayerHitByChicken1.wav</ShortName>
							<Path>SFX\Chicken\Attack\PlayerHitByChicken1_10C4C929.wem</Path>
						</File>
					</IncludedMemoryFiles>
					<SwitchContainers>
						<SwitchContainer SwitchValue="{3A2B8A51-89F7-4E53-A5E7-4F05BB0FD04F}">
							<Media>
								<File Id="44541559"/>
								<File Id="229165378"/>
								<File Id="468032026"/>
								<File Id="709017288"/>
								<File Id="715216894"/>
								<File Id="835120531"/>
							</Media>
						</SwitchContainer>
						<SwitchContainer SwitchValue="{A938E3BF-7195-4CAF-8DD8-F2B12A66A2AD}">
							<Media>
								<File Id="218867492"/>
								<File Id="898080531"/>
							</Media>
						</SwitchContainer>
					</SwitchContainers>
				</Event>
				<Event Id="1603074503" Name="PlayFacelessAttack" ObjectPath="\Events\Enemies\FacelessGirl\PlayFacelessAttack" MaxAttenuation="40.000000" DurationType="Infinite">
					<IncludedMemoryFiles>
						<File Id="275463776" Language="SFX">
							<ShortName>Faceless girl\Attack1.wav</ShortName>
							<Path>SFX\Faceless girl\Attack1_EA834667.wem</Path>
						</File>
					</IncludedMemoryFiles>
				</Event>
				<Event Id="740851443" Name="PlayFacelessDie" ObjectPath="\Events\Enemies\FacelessGirl\PlayFacelessDie" MaxAttenuation="40.000000" DurationType="OneShot" DurationMin="2.602177" DurationMax="2.602177">
					<IncludedMemoryFiles>
						<File Id="511328350" Language="SFX">
							<ShortName>Faceless girl\Die1.wav</ShortName>
							<Path>SFX\Faceless girl\Die1_10C4C929.wem</Path>
						</File>
					</IncludedMemoryFiles>
				</Event>
				<Event Id="1103033384" Name="PlayFacelessFootsteps" ObjectPath="\Events\Enemies\FacelessGirl\PlayFacelessFootsteps" MaxAttenuation="40.000000" DurationType="OneShot" DurationMin="0.377211" DurationMax="0.467007">
					<IncludedMemoryFiles>
						<File Id="475944744" Language="SFX">
							<ShortName>Faceless girl\footsteps 3.1.wav</ShortName>
							<Path>SFX\Faceless girl\footsteps 3.1_10C4C929.wem</Path>
						</File>
						<File Id="838426061" Language="SFX">
							<ShortName>Faceless girl\footsteps 3.2.wav</ShortName>
							<Path>SFX\Faceless girl\footsteps 3.2_10C4C929.wem</Path>
						</File>
					</IncludedMemoryFiles>
				</Event>
				<Event Id="3273151456" Name="PlayFacelessHurt" ObjectPath="\Events\Enemies\FacelessGirl\PlayFacelessHurt" MaxAttenuation="40.000000" DurationType="OneShot" DurationMin="1.000000" DurationMax="1.000000">
					<IncludedMemoryFiles>
						<File Id="144922140" Language="SFX">
							<ShortName>Faceless girl\Hurt1.wav</ShortName>
							<Path>SFX\Faceless girl\Hurt1_10C4C929.wem</Path>
						</File>
					</IncludedMemoryFiles>
				</Event>
				<Event Id="2474406794" Name="PlayFacelessMoan" ObjectPath="\Events\Enemies\FacelessGirl\PlayFacelessMoan" MaxAttenuation="40.000000" DurationType="OneShot" DurationMin="1.500000" DurationMax="2.300000">
					<IncludedMemoryFiles>
						<File Id="220696934" Language="SFX">
							<ShortName>Faceless girl\Moan2.wav</ShortName>
							<Path>SFX\Faceless girl\Moan2_10C4C929.wem</Path>
						</File>
						<File Id="599470771" Language="SFX">
							<ShortName>Faceless girl\Moan3.wav</ShortName>
							<Path>SFX\Faceless girl\Moan3_10C4C929.wem</Path>
						</File>
						<File Id="843313399" Language="SFX">
							<ShortName>Faceless girl\Moan1.wav</ShortName>
							<Path>SFX\Faceless girl\Moan1_10C4C929.wem</Path>
						</File>
					</IncludedMemoryFiles>
				</Event>
				<Event Id="1241118191" Name="PlayFootstepsPlayer" ObjectPath="\Events\Players\PlayFootstepsPlayer" MaxAttenuation="40.000000" DurationType="OneShot" DurationMin="0.142217" DurationMax="0.473162">
					<IncludedMemoryFiles>
						<File Id="47477698" Language="SFX">
							<ShortName>PlayerMovement\Gyaru\SapatoFormalGrassBackwards1.wav</ShortName>
							<Path>SFX\PlayerMovement\Gyaru\SapatoFormalGrassBackwards1_10C4C929.wem</Path>
						</File>
						<File Id="50675186" Language="SFX">
							<ShortName>PlayerMovement\Gyaru\SapatoFormalDirtWalk1.wav</ShortName>
							<Path>SFX\PlayerMovement\Gyaru\SapatoFormalDirtWalk1_10C4C929.wem</Path>
						</File>
						<File Id="55011284" Language="SFX">
							<ShortName>PlayerMovement\Gyaru\SapatoFormalDirtRun1.wav</ShortName>
							<Path>SFX\PlayerMovement\Gyaru\SapatoFormalDirtRun1_10C4C929.wem</Path>
						</File>
						<File Id="92101835" Language="SFX">
							<ShortName>PlayerMovement\Gyaru\SapatoFormalBackwards1.wav</ShortName>
							<Path>SFX\PlayerMovement\Gyaru\SapatoFormalBackwards1_10C4C929.wem</Path>
						</File>
						<File Id="93558507" Language="SFX">
							<ShortName>PlayerMovement\Gyaru\SapatoFormalRun4.wav</ShortName>
							<Path>SFX\PlayerMovement\Gyaru\SapatoFormalRun4_10C4C929.wem</Path>
						</File>
						<File Id="108683262" Language="SFX">
							<ShortName>PlayerMovement\Gyaru\SapatoFormalGrassWalk4.wav</ShortName>
							<Path>SFX\PlayerMovement\Gyaru\SapatoFormalGrassWalk4_10C4C929.wem</Path>
						</File>
						<File Id="155334950" Language="SFX">
							<ShortName>PlayerMovement\Gyaru\SapatoFormalDirtBack1.wav</ShortName>
							<Path>SFX\PlayerMovement\Gyaru\SapatoFormalDirtBack1_7D283704.wem</Path>
						</File>
						<File Id="284649697" Language="SFX">
							<ShortName>PlayerMovement\Gyaru\SapatoFormalAlcatrãoWalk1.wav</ShortName>
							<Path>SFX\PlayerMovement\Gyaru\SapatoFormalAlcatrãoWalk1_10C4C929.wem</Path>
						</File>
						<File Id="388498135" Language="SFX">
							<ShortName>PlayerMovement\Gyaru\SapatoFormalDirtBack2.wav</ShortName>
							<Path>SFX\PlayerMovement\Gyaru\SapatoFormalDirtBack2_10C4C929.wem</Path>
						</File>
						<File Id="397601067" Language="SFX">
							<ShortName>PlayerMovement\Gyaru\SapatoFormalAlcatrãoRun2.wav</ShortName>
							<Path>SFX\PlayerMovement\Gyaru\SapatoFormalAlcatrãoRun2_10C4C929.wem</Path>
						</File>
						<File Id="415192423" Language="SFX">
							<ShortName>PlayerMovement\Gyaru\SapatoFormalWalk1.wav</ShortName>
							<Path>SFX\PlayerMovement\Gyaru\SapatoFormalWalk1_10C4C929.wem</Path>
						</File>
						<File Id="427787522" Language="SFX">
							<ShortName>PlayerMovement\Gyaru\SapatoFormalSidewalkWalk2.wav</ShortName>
							<Path>SFX\PlayerMovement\Gyaru\SapatoFormalSidewalkWalk2_10C4C929.wem</Path>
						</File>
						<File Id="430418663" Language="SFX">
							<ShortName>PlayerMovement\Gyaru\SapatoFormalGrassRun1.wav</ShortName>
							<Path>SFX\PlayerMovement\Gyaru\SapatoFormalGrassRun1_10C4C929.wem</Path>
						</File>
						<File Id="488739457" Language="SFX">
							<ShortName>PlayerMovement\Gyaru\SapatoFormalBackwards2.wav</ShortName>
							<Path>SFX\PlayerMovement\Gyaru\SapatoFormalBackwards2_10C4C929.wem</Path>
						</File>
						<File Id="604779897" Language="SFX">
							<ShortName>PlayerMovement\Gyaru\SapatoFormalGrassWalk2.wav</ShortName>
							<Path>SFX\PlayerMovement\Gyaru\SapatoFormalGrassWalk2_10C4C929.wem</Path>
						</File>
						<File Id="607877876" Language="SFX">
							<ShortName>PlayerMovement\Gyaru\SapatoFormalSidewalkRun2.wav</ShortName>
							<Path>SFX\PlayerMovement\Gyaru\SapatoFormalSidewalkRun2_10C4C929.wem</Path>
						</File>
						<File Id="618783911" Language="SFX">
							<ShortName>PlayerMovement\Gyaru\SapatoFormalGrassRun2.wav</ShortName>
							<Path>SFX\PlayerMovement\Gyaru\SapatoFormalGrassRun2_10C4C929.wem</Path>
						</File>
						<File Id="662521244" Language="SFX">
							<ShortName>PlayerMovement\Gyaru\SapatoFormalAlcatrãoWalk2.wav</ShortName>
							<Path>SFX\PlayerMovement\Gyaru\SapatoFormalAlcatrãoWalk2_10C4C929.wem</Path>
						</File>
						<File Id="669793138" Language="SFX">
							<ShortName>PlayerMovement\Gyaru\SapatoFormalSidewalkWalk1.wav</ShortName>
							<Path>SFX\PlayerMovement\Gyaru\SapatoFormalSidewalkWalk1_10C4C929.wem</Path>
						</File>
						<File Id="734962289" Language="SFX">
							<ShortName>PlayerMovement\Gyaru\SapatoFormalAlcatrãoRun1.wav</ShortName>
							<Path>SFX\PlayerMovement\Gyaru\SapatoFormalAlcatrãoRun1_10C4C929.wem</Path>
						</File>
						<File Id="770698417" Language="SFX">
							<ShortName>PlayerMovement\Gyaru\SapatoFormalWalk2.wav</ShortName>
							<Path>SFX\PlayerMovement\Gyaru\SapatoFormalWalk2_10C4C929.wem</Path>
						</File>
						<File Id="802531233" Language="SFX">
							<ShortName>PlayerMovement\Gyaru\SapatoFormalGrassRun3.wav</ShortName>
							<Path>SFX\PlayerMovement\Gyaru\SapatoFormalGrassRun3_10C4C929.wem</Path>
						</File>
						<File Id="830714985" Language="SFX">
							<ShortName>PlayerMovement\Gyaru\SapatoFormalGrassBackwards2.wav</ShortName>
							<Path>SFX\PlayerMovement\Gyaru\SapatoFormalGrassBackwards2_10C4C929.wem</Path>
						</File>
						<File Id="845557366" Language="SFX">
							<ShortName>PlayerMovement\Gyaru\SapatoFormalGrassWalk1.wav</ShortName>
							<Path>SFX\PlayerMovement\Gyaru\SapatoFormalGrassWalk1_10C4C929.wem</Path>
						</File>
						<File Id="854749403" Language="SFX">
							<ShortName>PlayerMovement\Gyaru\SapatoFormalSidewalkBack2.wav</ShortName>
							<Path>SFX\PlayerMovement\Gyaru\SapatoFormalSidewalkBack2_10C4C929.wem</Path>
						</File>
						<File Id="854826965" Language="SFX">
							<ShortName>PlayerMovement\Gyaru\SapatoFormalDirtWalk2.wav</ShortName>
							<Path>SFX\PlayerMovement\Gyaru\SapatoFormalDirtWalk2_10C4C929.wem</Path>
						</File>
						<File Id="866266268" Language="SFX">
							<ShortName>PlayerMovement\Gyaru\SapatoFormalRun3.wav</ShortName>
							<Path>SFX\PlayerMovement\Gyaru\SapatoFormalRun3_10C4C929.wem</Path>
						</File>
						<File Id="921916641" Language="SFX">
							<ShortName>PlayerMovement\Gyaru\SapatoFormalSidewalkRun1.wav</ShortName>
							<Path>SFX\PlayerMovement\Gyaru\SapatoFormalSidewalkRun1_10C4C929.wem</Path>
						</File>
						<File Id="955760206" Language="SFX">
							<ShortName>PlayerMovement\Gyaru\SapatoFormalAlcatrãoBack2.wav</ShortName>
							<Path>SFX\PlayerMovement\Gyaru\SapatoFormalAlcatrãoBack2_10C4C929.wem</Path>
						</File>
						<File Id="973497115" Language="SFX">
							<ShortName>PlayerMovement\Gyaru\SapatoFormalGrassWalk3.wav</ShortName>
							<Path>SFX\PlayerMovement\Gyaru\SapatoFormalGrassWalk3_10C4C929.wem</Path>
						</File>
						<File Id="976003160" Language="SFX">
							<ShortName>PlayerMovement\Gyaru\SapatoFormalDirtRun2.wav</ShortName>
							<Path>SFX\PlayerMovement\Gyaru\SapatoFormalDirtRun2_10C4C929.wem</Path>
						</File>
						<File Id="990394786" Language="SFX">
							<ShortName>PlayerMovement\Gyaru\SapatoFormalSidewalkBack1.wav</ShortName>
							<Path>SFX\PlayerMovement\Gyaru\SapatoFormalSidewalkBack1_10C4C929.wem</Path>
						</File>
						<File Id="1072860399" Language="SFX">
							<ShortName>PlayerMovement\Gyaru\SapatoFormalAlcatrãoBack1.wav</ShortName>
							<Path>SFX\PlayerMovement\Gyaru\SapatoFormalAlcatrãoBack1_10C4C929.wem</Path>
						</File>
					</IncludedMemoryFiles>
					<DefaultSwitchValue>{FE874951-659B-4E08-AC9B-A2268D72415F}</DefaultSwitchValue>
					<SwitchContainers>
						<SwitchContainer SwitchValue="{FE874951-659B-4E08-AC9B-A2268D72415F}">
							<DefaultSwitchValue>{EADB2145-6556-4F1E-8CEE-2F298442AE74}</DefaultSwitchValue>
							<Children>
								<SwitchContainer SwitchValue="{EADB2145-6556-4F1E-8CEE-2F298442AE74}">
									<DefaultSwitchValue>{C561F1D4-D0FA-459F-86B1-F067C3B54EDC}</DefaultSwitchValue>
									<Children>
										<SwitchContainer SwitchValue="{C561F1D4-D0FA-459F-86B1-F067C3B54EDC}">
											<Media>
												<File Id="415192423"/>
												<File Id="770698417"/>
											</Media>
										</SwitchContainer>
										<SwitchContainer SwitchValue="{685B8CBA-54CD-41E3-A875-055E33058A9F}">
											<Media>
												<File Id="93558507"/>
												<File Id="866266268"/>
											</Media>
										</SwitchContainer>
										<SwitchContainer SwitchValue="{6F7D7988-C6AF-4AE1-9021-9D0E65AEDBB8}">
											<Media>
												<File Id="92101835"/>
												<File Id="488739457"/>
											</Media>
										</SwitchContainer>
									</Children>
								</SwitchContainer>
								<SwitchContainer SwitchValue="{CC89284F-9036-4382-ADE6-BC3DAA5D8D81}">
									<DefaultSwitchValue>{C561F1D4-D0FA-459F-86B1-F067C3B54EDC}</DefaultSwitchValue>
									<Children>
										<SwitchContainer SwitchValue="{685B8CBA-54CD-41E3-A875-055E33058A9F}">
											<Media>
												<File Id="430418663"/>
												<File Id="618783911"/>
												<File Id="802531233"/>
											</Media>
										</SwitchContainer>
										<SwitchContainer SwitchValue="{C561F1D4-D0FA-459F-86B1-F067C3B54EDC}">
											<Media>
												<File Id="108683262"/>
												<File Id="604779897"/>
												<File Id="845557366"/>
												<File Id="973497115"/>
											</Media>
										</SwitchContainer>
										<SwitchContainer SwitchValue="{6F7D7988-C6AF-4AE1-9021-9D0E65AEDBB8}">
											<Media>
												<File Id="47477698"/>
												<File Id="830714985"/>
											</Media>
										</SwitchContainer>
									</Children>
								</SwitchContainer>
								<SwitchContainer SwitchValue="{A5C00AF5-760A-43AC-ADC8-27752D9FF735}">
									<Children>
										<SwitchContainer SwitchValue="{C561F1D4-D0FA-459F-86B1-F067C3B54EDC}">
											<Media>
												<File Id="284649697"/>
												<File Id="662521244"/>
											</Media>
										</SwitchContainer>
										<SwitchContainer SwitchValue="{685B8CBA-54CD-41E3-A875-055E33058A9F}">
											<Media>
												<File Id="397601067"/>
												<File Id="734962289"/>
											</Media>
										</SwitchContainer>
										<SwitchContainer SwitchValue="{6F7D7988-C6AF-4AE1-9021-9D0E65AEDBB8}">
											<Media>
												<File Id="955760206"/>
												<File Id="1072860399"/>
											</Media>
										</SwitchContainer>
									</Children>
								</SwitchContainer>
								<SwitchContainer SwitchValue="{8EDADF13-DE69-4F1A-AF53-F9DAFFB4EA70}">
									<Children>
										<SwitchContainer SwitchValue="{C561F1D4-D0FA-459F-86B1-F067C3B54EDC}">
											<Media>
												<File Id="50675186"/>
												<File Id="854826965"/>
											</Media>
										</SwitchContainer>
										<SwitchContainer SwitchValue="{685B8CBA-54CD-41E3-A875-055E33058A9F}">
											<Media>
												<File Id="55011284"/>
												<File Id="976003160"/>
											</Media>
										</SwitchContainer>
										<SwitchContainer SwitchValue="{6F7D7988-C6AF-4AE1-9021-9D0E65AEDBB8}">
											<Media>
												<File Id="155334950"/>
												<File Id="388498135"/>
											</Media>
										</SwitchContainer>
									</Children>
								</SwitchContainer>
								<SwitchContainer SwitchValue="{E40B73BF-197F-4B94-86EF-69CE4B898531}">
									<Children>
										<SwitchContainer SwitchValue="{C561F1D4-D0FA-459F-86B1-F067C3B54EDC}">
											<Media>
												<File Id="427787522"/>
												<File Id="669793138"/>
											</Media>
										</SwitchContainer>
										<SwitchContainer SwitchValue="{685B8CBA-54CD-41E3-A875-055E33058A9F}">
											<Media>
												<File Id="607877876"/>
												<File Id="921916641"/>
											</Media>
										</SwitchContainer>
										<SwitchContainer SwitchValue="{6F7D7988-C6AF-4AE1-9021-9D0E65AEDBB8}">
											<Media>
												<File Id="854749403"/>
												<File Id="990394786"/>
											</Media>
										</SwitchContainer>
									</Children>
								</SwitchContainer>
							</Children>
						</SwitchContainer>
					</SwitchContainers>
				</Event>
				<Event Id="4106886787" Name="PlayFSChicken" ObjectPath="\Events\Tests\Chicken\PlayFSChicken" MaxAttenuation="0.000000" DurationType="OneShot" DurationMin="0.000000" DurationMax="0.000000"/>
				<Event Id="2613825061" Name="PlayGiggleChicken" ObjectPath="\Events\Tests\Chicken\PlayGiggleChicken" MaxAttenuation="0.000000" DurationType="OneShot" DurationMin="0.000000" DurationMax="0.000000"/>
				<Event Id="145167493" Name="PlayHighlight" ObjectPath="\Events\Tests\Menu\PlayHighlight" DurationType="OneShot" DurationMin="0.266259" DurationMax="0.266259">
					<IncludedMemoryFiles>
						<File Id="697333511" Language="SFX">
							<ShortName>Main Menu Highlight.wav</ShortName>
							<Path>SFX\Main Menu Highlight_10C4C929.wem</Path>
						</File>
					</IncludedMemoryFiles>
				</Event>
				<Event Id="4251718543" Name="PlayHitChicken" ObjectPath="\Events\Tests\Chicken\PlayHitChicken" MaxAttenuation="0.000000" DurationType="OneShot" DurationMin="0.000000" DurationMax="0.000000"/>
				<Event Id="1168436793" Name="PlayKeypress" ObjectPath="\Events\Tests\Menu\PlayKeypress" DurationType="OneShot" DurationMin="0.149773" DurationMax="0.149773">
					<IncludedMemoryFiles>
						<File Id="26955166" Language="SFX">
							<ShortName>Main Menu Keypress.wav</ShortName>
							<Path>SFX\Main Menu Keypress_10C4C929.wem</Path>
						</File>
					</IncludedMemoryFiles>
				</Event>
				<Event Id="539806209" Name="PlayMirrorProp" ObjectPath="\Events\Players\Gyaru\PlayMirrorProp" MaxAttenuation="40.000000" DurationType="OneShot" DurationMin="0.500000" DurationMax="0.500000">
					<IncludedMemoryFiles>
						<File Id="434715277" Language="SFX">
							<ShortName>Player props\espelho.wav</ShortName>
							<Path>SFX\Player props\espelho_10C4C929.wem</Path>
						</File>
					</IncludedMemoryFiles>
				</Event>
				<Event Id="2575517534" Name="PlayPhoneProp" ObjectPath="\Events\Players\Gyaru\PlayPhoneProp" MaxAttenuation="40.000000" DurationType="OneShot" DurationMin="0.092311" DurationMax="0.109777">
					<IncludedMemoryFiles>
						<File Id="394513528" Language="SFX">
							<ShortName>Player props\teclado.wav</ShortName>
							<Path>SFX\Player props\teclado_10C4C929.wem</Path>
						</File>
					</IncludedMemoryFiles>
				</Event>
				<Event Id="1870077814" Name="PlayWardenDie" ObjectPath="\Events\Enemies\Warden\PlayWardenDie" MaxAttenuation="40.000000" DurationType="OneShot" DurationMin="1.035170" DurationMax="1.035170">
					<IncludedMemoryFiles>
						<File Id="707779245" Language="SFX">
							<ShortName>Shards\Vocalization\ImDie.wav</ShortName>
							<Path>SFX\Shards\Vocalization\ImDie_10C4C929.wem</Path>
						</File>
					</IncludedMemoryFiles>
				</Event>
				<Event Id="933827407" Name="PlayWardenHurt" ObjectPath="\Events\Enemies\Warden\PlayWardenHurt" MaxAttenuation="40.000000" DurationType="OneShot" DurationMin="0.458502" DurationMax="0.545254">
					<IncludedMemoryFiles>
						<File Id="366868527" Language="SFX">
							<ShortName>Shards\Vocalization\Hurt1.2.wav</ShortName>
							<Path>SFX\Shards\Vocalization\Hurt1.2_800E7558.wem</Path>
						</File>
						<File Id="875954542" Language="SFX">
							<ShortName>Shards\Vocalization\Hurt2.2.wav</ShortName>
							<Path>SFX\Shards\Vocalization\Hurt2.2_427CEEB8.wem</Path>
						</File>
					</IncludedMemoryFiles>
				</Event>
				<Event Id="2920750754" Name="PlayWardenIdle" ObjectPath="\Events\Enemies\Warden\PlayWardenIdle" MaxAttenuation="40.000000" DurationType="Infinite">
					<IncludedMemoryFiles>
						<File Id="535913784" Language="SFX">
							<ShortName>Shards\warden idle.wav</ShortName>
							<Path>SFX\Shards\warden idle_C0BF7146.wem</Path>
						</File>
					</IncludedMemoryFiles>
				</Event>
				<Event Id="3781044531" Name="PlayWardenMove" ObjectPath="\Events\Enemies\Warden\PlayWardenMove" MaxAttenuation="40.000000" DurationType="Infinite">
					<IncludedMemoryFiles>
						<File Id="731462982" Language="SFX">
							<ShortName>Shards\warden move.wav</ShortName>
							<Path>SFX\Shards\warden move_C95F6BD6.wem</Path>
						</File>
					</IncludedMemoryFiles>
				</Event>
				<Event Id="1171015393" Name="PlayWardenSpawn" ObjectPath="\Events\Enemies\Warden\PlayWardenSpawn" MaxAttenuation="40.000000" DurationType="OneShot" DurationMin="7.525202" DurationMax="7.525202">
					<IncludedMemoryFiles>
						<File Id="832214079" Language="SFX">
							<ShortName>Shards\warden spawn.wav</ShortName>
							<Path>SFX\Shards\warden spawn_E1760C21.wem</Path>
						</File>
					</IncludedMemoryFiles>
				</Event>
				<Event Id="2951433145" Name="ShardsRise" ObjectPath="\Events\Enemies\Warden\ShardsRise" MaxAttenuation="40.000000" DurationType="OneShot" DurationMin="5.000000" DurationMax="8.500000">
					<IncludedMemoryFiles>
						<File Id="784850670" Language="SFX">
							<ShortName>Shards\shards rising 3.wav</ShortName>
							<Path>SFX\Shards\shards rising 3_10C4C929.wem</Path>
						</File>
						<File Id="795602171" Language="SFX">
							<ShortName>Shards\shards rising.wav</ShortName>
							<Path>SFX\Shards\shards rising_10C4C929.wem</Path>
						</File>
						<File Id="1073491051" Language="SFX">
							<ShortName>Shards\shards rising 2.wav</ShortName>
							<Path>SFX\Shards\shards rising 2_10C4C929.wem</Path>
						</File>
					</IncludedMemoryFiles>
				</Event>
				<Event Id="617402058" Name="ShardsThrow" ObjectPath="\Events\Enemies\Warden\ShardsThrow" MaxAttenuation="40.000000" DurationType="OneShot" DurationMin="3.303560" DurationMax="5.297316">
					<IncludedMemoryFiles>
						<File Id="243879499" Language="SFX">
							<ShortName>Shards\shards throw5.wav</ShortName>
							<Path>SFX\Shards\shards throw5_10C4C929.wem</Path>
						</File>
						<File Id="504518702" Language="SFX">
							<ShortName>Shards\shards throw4.wav</ShortName>
							<Path>SFX\Shards\shards throw4_10C4C929.wem</Path>
						</File>
						<File Id="628974826" Language="SFX">
							<ShortName>Shards\shards throw2.wav</ShortName>
							<Path>SFX\Shards\shards throw2_10C4C929.wem</Path>
						</File>
						<File Id="648114941" Language="SFX">
							<ShortName>Shards\shards throw1.wav</ShortName>
							<Path>SFX\Shards\shards throw1_10C4C929.wem</Path>
						</File>
						<File Id="685506779" Language="SFX">
							<ShortName>Shards\shards throw3.wav</ShortName>
							<Path>SFX\Shards\shards throw3_10C4C929.wem</Path>
						</File>
					</IncludedMemoryFiles>
				</Event>
				<Event Id="3796699282" Name="ShardWallHit" ObjectPath="\Events\Enemies\Warden\ShardWallHit" DurationType="OneShot" DurationMin="1.500000" DurationMax="1.500000">
					<IncludedMemoryFiles>
						<File Id="179151226" Language="SFX">
							<ShortName>Shards\shard wall hit 5.wav</ShortName>
							<Path>SFX\Shards\shard wall hit 5_10C4C929.wem</Path>
						</File>
						<File Id="264203001" Language="SFX">
							<ShortName>Shards\shard wall hit 1.wav</ShortName>
							<Path>SFX\Shards\shard wall hit 1_10C4C929.wem</Path>
						</File>
						<File Id="509966098" Language="SFX">
							<ShortName>Shards\shard wall hit 3.wav</ShortName>
							<Path>SFX\Shards\shard wall hit 3_10C4C929.wem</Path>
						</File>
						<File Id="792448310" Language="SFX">
							<ShortName>Shards\shard wall hit 4.wav</ShortName>
							<Path>SFX\Shards\shard wall hit 4_10C4C929.wem</Path>
						</File>
						<File Id="1003048111" Language="SFX">
							<ShortName>Shards\shard wall hit 6.wav</ShortName>
							<Path>SFX\Shards\shard wall hit 6_10C4C929.wem</Path>
						</File>
						<File Id="1064002268" Language="SFX">
							<ShortName>Shards\shard wall hit 2.wav</ShortName>
							<Path>SFX\Shards\shard wall hit 2_10C4C929.wem</Path>
						</File>
					</IncludedMemoryFiles>
				</Event>
				<Event Id="2779602813" Name="StopAllGameObject" ObjectPath="\Events\Others\StopAllGameObject" MaxAttenuation="0.000000" DurationType="OneShot" DurationMin="0.000000" DurationMax="0.000000"/>
				<Event Id="4052641749" Name="StopFacelessAttack" ObjectPath="\Events\Enemies\FacelessGirl\StopFacelessAttack" MaxAttenuation="40.000000" DurationType="OneShot" DurationMin="1.500000" DurationMax="1.500000">
					<IncludedMemoryFiles>
						<File Id="698868433" Language="SFX">
							<ShortName>Faceless girl\AttackTail.wav</ShortName>
							<Path>SFX\Faceless girl\AttackTail_63C012F9.wem</Path>
						</File>
					</IncludedMemoryFiles>
				</Event>
				<Event Id="4217165871" Name="StopMovementSound" ObjectPath="\Events\Enemies\Warden\StopMovementSound" MaxAttenuation="0.000000" DurationType="OneShot" DurationMin="0.000000" DurationMax="0.000000"/>
				<Event Id="3241046308" Name="TestBass" ObjectPath="\Events\Tests\TestBass" MaxAttenuation="40.000000" DurationType="Infinite">
					<IncludedMemoryFiles>
						<File Id="479465834" Language="SFX">
							<ShortName>chase bass.wav</ShortName>
							<Path>SFX\chase bass_D79FB2B7.wem</Path>
						</File>
					</IncludedMemoryFiles>
				</Event>
				<Event Id="1813814736" Name="WeirdAttack" ObjectPath="\Events\Tests\Chicken\WeirdAttack" MaxAttenuation="0.000000" DurationType="OneShot" DurationMin="0.000000" DurationMax="0.000000"/>
			</IncludedEvents>
			<GameParameters>
				<GameParameter Id="222722569" Name="RTPC_Occlusion_LoPass" ObjectPath="\Game Parameters\Default Work Unit\RTPC_Occlusion_LoPass"/>
				<GameParameter Id="342905355" Name="RTPC_Occlusion_Volume" ObjectPath="\Game Parameters\Default Work Unit\RTPC_Occlusion_Volume"/>
			</GameParameters>
			<SwitchGroups>
				<SwitchGroup Id="690777561" Name="WalkRun" ObjectPath="\Switches\Default Work Unit\WalkRun">
					<Switches>
						<Switch Id="2108779966" Name="Walk" ObjectPath="\Switches\Default Work Unit\WalkRun\Walk"/>
						<Switch Id="712161704" Name="Run" ObjectPath="\Switches\Default Work Unit\WalkRun\Run"/>
						<Switch Id="3876169137" Name="Backwards" ObjectPath="\Switches\Default Work Unit\WalkRun\Backwards"/>
					</Switches>
				</SwitchGroup>
				<SwitchGroup Id="977351599" Name="PlayerName" ObjectPath="\Switches\Default Work Unit\PlayerName">
					<Switches>
						<Switch Id="414889065" Name="Gyaru" ObjectPath="\Switches\Default Work Unit\PlayerName\Gyaru"/>
					</Switches>
				</SwitchGroup>
				<SwitchGroup Id="3072116243" Name="GroundMaterial" ObjectPath="\Switches\Default Work Unit\GroundMaterial">
					<Switches>
						<Switch Id="1160234136" Name="Normal" ObjectPath="\Switches\Default Work Unit\GroundMaterial\Normal"/>
						<Switch Id="491961918" Name="Forest" ObjectPath="\Switches\Default Work Unit\GroundMaterial\Forest"/>
						<Switch Id="2830102203" Name="Pavement" ObjectPath="\Switches\Default Work Unit\GroundMaterial\Pavement"/>
						<Switch Id="3137249879" Name="Sidewalk" ObjectPath="\Switches\Default Work Unit\GroundMaterial\Sidewalk"/>
						<Switch Id="2195636714" Name="Dirt" ObjectPath="\Switches\Default Work Unit\GroundMaterial\Dirt"/>
					</Switches>
				</SwitchGroup>
				<SwitchGroup Id="3765388645" Name="PlayerHitSwitch" ObjectPath="\Switches\Default Work Unit\PlayerHitSwitch">
					<Switches>
						<Switch Id="4251222990" Name="Chicken" ObjectPath="\Switches\Default Work Unit\PlayerHitSwitch\Chicken"/>
						<Switch Id="2986888339" Name="Shard" ObjectPath="\Switches\Default Work Unit\PlayerHitSwitch\Shard"/>
					</Switches>
				</SwitchGroup>
			</SwitchGroups>
		</SoundBank>
		<SoundBank Id="3161908922" Language="SFX" Hash="2348770020">
			<ObjectPath>\SoundBanks\Default Work Unit\Main</ObjectPath>
			<ShortName>Main</ShortName>
			<Path>Main.bnk</Path>
		</SoundBank>
	</SoundBanks>
</SoundBanksInfo>
